helloIndia/__init__.py
helloIndia/helloindia.py
helloindia-0.0.3.dist-info/METADATA
helloindia-0.0.3.dist-info/WHEEL
helloindia-0.0.3.dist-info/top_level.txt
helloindia-0.0.3.dist-info/RECORD
