Metadata-Version: 2.1
Name: helloindia
Version: 0.0.3
Summary: A basic hello package
Home-page: UNKNOWN
Author: Shivam Mansukh
Author-email: <shivammansukh33@gmail.com>
License: UNKNOWN
Keywords: python,hello,India,hello India
Platform: UNKNOWN
Classifier: Development Status :: 1 - Planning
Classifier: Intended Audience :: Developers
Classifier: Programming Language :: Python :: 3
Classifier: Operating System :: Unix
Classifier: Operating System :: MacOS :: MacOS X
Classifier: Operating System :: Microsoft :: Windows
